{
"info": {
"name": "Stock Management API",
"schema": "[https://schema.getpostman.com/json/collection/v2.1.0/collection.json](https://schema.getpostman.com/json/collection/v2.1.0/collection.json)"
},
"item": [
{
"name": "Add Product",
"request": {
"method": "POST",
"header": [
{"key": "Content-Type", "value": "application/json"}
],
"body": {
"mode": "raw",
"raw": "{\n  "name": "Pen",\n  "price": 10,\n  "stock": 50\n}"
},
"url": {"raw": "http://localhost:3000/api/products", "protocol": "http", "host": ["localhost"], "port": "3000", "path": ["api", "products"]}
}
},
{
"name": "List Products",
"request": {
"method": "GET",
"url": {"raw": "http://localhost:3000/api/products", "protocol": "http", "host": ["localhost"], "port": "3000", "path": ["api", "products"]}
}
},
{
"name": "Create Order",
"request": {
"method": "POST",
"header": [{"key": "Content-Type", "value": "application/json"}],
"body": {
"mode": "raw",
"raw": "{\n  "userName": "Alice",\n  "products": [\n    { "productId": "<insert_product_id_here>", "qty": 5 }\n  ]\n}"
},
"url": {"raw": "http://localhost:3000/api/orders", "protocol": "http", "host": ["localhost"], "port": "3000", "path": ["api", "orders"]}
}
},
{
"name": "List Orders",
"request": {
"method": "GET",
"url": {"raw": "http://localhost:3000/api/orders", "protocol": "http", "host": ["localhost"], "port": "3000", "path": ["api", "orders"]}
}
}
]
}
